Workbook

Sheet Task_Master
A1: Task_ID | B1: Process | C1: Task_Name | D1: Owner_Department | E1: Dependency | F1: Planned_Day
A2: 1 | B2: AP | C2: Vendor Invoice Posting | D2: Accounts Payable | E2: None | F2: 2
A3: 2 | B3: AP | C3: AP Reconciliation | D3: Accounts Payable | E3: 1 | F3: 5
A4: 3 | B4: AR | C4: Customer Invoice Posting | D4: Accounts Receivable | E4: None | F4: 2
A5: 4 | B5: AR | C5: AR Reconciliation | D5: Accounts Receivable | E5: 3 | F5: 6
A6: 5 | B6: Payroll | C6: Salary Processing | D6: HR/Payroll | E6: None | F6: 3
A7: 6 | B7: Payroll | C7: Payroll Journal Entry | D7: Finance | E7: 5 | F7: 6
A8: 7 | B8: Inventory | C8: Inventory Count | D8: Operations | E8: None | F8: 4
A9: 8 | B9: Inventory | C9: Inventory Valuation | D9: Finance | E9: 7 | F9: 7
A10: 9 | B10: Cash | C10: Bank Reconciliation | D10: Treasury | E10: 1,3 | F10: 7
A11: 10 | B11: Fixed Assets | C11: Depreciation Run | D11: Finance | E11: None | F11: 6
A12: 11 | B12: Accruals | C12: Expense Accrual Posting | D12: Finance | E12: 2,4,8 | F12: 8
A13: 12 | B13: Reporting | C13: Trial Balance Review | D13: Finance | E13: 6,9,10,11 | F13: 9
A14: 13 | B14: Reporting | C14: Financial Statement Prep | D14: Finance | E14: 12 | F14: 10
A15: 14 | B15: Reporting | C15: Management Review | D15: CFO Office | E15: 13 | F15: 11
A16: 15 | B16: Reporting | C16: Books Closed | D16: Finance | E16: 14 | F16: 12

Sheet Sheet1
A3: Row Labels | B3: Average of Delay by Close Title
A4: Inventory Valuation | B4: 2
A5: Expense Accrual Posting | B5: 2
A6: Salary Processing | B6: 1.6666667
A7: Bank Reconciliation | B7: 1.6666667
A8: AP Reconciliation | B8: 1.6666667
A9: Financial Statement Prep | B9: 1.6666667
A10: Trial Balance Review | B10: 1.3333333
A11: Payroll Journal Entry | B11: 1.3333333
A12: Books Closed | B12: 1.3333333
A13: Inventory Count | B13: 1.3333333
A14: Vendor Invoice Posting | B14: 1
A15: Depreciation Run | B15: 1
... A19: Grand Total | B19: 1.2888889

Sheet Sheet2
A3: Row Labels | B3: Average of Delay
A4: Accounts Payable | B4: 1.3333333
A5: Accounts Receivable | B5: 0.16666667
A6: CFO Office | B6: 1
A7: Finance | B7: 1.5238095
A8: HR/Payroll | B8: 1.6666667
A9: Operations | B9: 1.3333333
A10: Treasury | B10: 1.6666667
A11: Grand Total | B11: 1.2888889

Sheet Sheet3
A3: Average of Delay | B3: Column Labels
A4: Row Labels | B4: Jan | C4: Feb | D4: Mar
A5: AP Reconciliation | B5: 1 | C5: 1 | D5: 3
A6: AR Reconciliation | B6: 0 | C6: 0 | D6: 0
A7: Bank Reconciliation | B7: 2 | C7: 0 | D7: 3
A8: Books Closed | B8: 0 | C8: 1 | D8: 3
A9: Customer Invoice Posting | B9: 0 | C9: 1 | D9: 0
A10: Depreciation Run | B10: 0 | C10: 3 | D10: 0
A11: Expense Accrual Posting | B11: 1 | C11: 3 | D11: 2
A12: Financial Statement Prep | B12: 1 | C12: 1 | D12: 3
A13: Inventory Count | B13: 3 | C13: 1 | D13: 0
A14: Inventory Valuation | B14: 2 | C14: 1 | D14: 3
A15: Management Review | B15: 0 | C15: 1 | D15: 2
A16: Payroll Journal Entry | B16: 1 | C16: 2 | D16: 1
... A20: Grand Total | B20: 0.93333333 | C20: 1.2 | D20: 1.7333333

Sheet Close_Data
A1: Month | B1: Task_ID | C1: Process | D1: Task_Name | E1: Owner_Department | F1: Dependency | G1: Planned_Day | H1: Actual_Day | I1: Delay | J1: Issue | K1: Start_Day | L1: Duration
A2: {=INDEX({"Jan","Feb","Mar"},ROUNDUP(ROW(A1)/15,0))} -> Jan | B2: {=INDEX(Task_Master!A$2:A$16,MOD(ROW()-2,15)+1)} -> 1 | C2: {=INDEX(Task_Master!B:B,MOD(ROW(A1)-1,15)+2)} -> AP | D2: {=INDEX(Task_Master!C:C,MOD(ROW(A1)-1,15)+2)} -> Vendor Invoice Posting | E2: {=INDEX(Task_Master!D:D,MOD(ROW(A1)-1,15)+2)} -> Accounts Payable | F2: {=INDEX(Task_Master!E:E,MOD(ROW(A1)-1,15)+2)} -> None | G2: 2 | H2: 2 | I2: =H2-G2 -> 0 | J2: =IF(I2=0,"On Time",IF(I2<=2,"Minor Delay","Major Delay")) -> On Time | K2: =H2-I2 -> 2 | L2: =IF(I2=0,0.3,I2) -> 0.3
A3: {=INDEX({"Jan","Feb","Mar"},ROUNDUP(ROW(A2)/15,0))} -> Jan | B3: {=INDEX(Task_Master!A$2:A$16,MOD(ROW()-2,15)+1)} -> 2 | C3: {=INDEX(Task_Master!B:B,MOD(ROW(A2)-1,15)+2)} -> AP | D3: {=INDEX(Task_Master!C:C,MOD(ROW(A2)-1,15)+2)} -> AP Reconciliation | E3: {=INDEX(Task_Master!D:D,MOD(ROW(A2)-1,15)+2)} -> Accounts Payable | F3: {=INDEX(Task_Master!E:E,MOD(ROW(A2)-1,15)+2)} -> 1 | G3: 4 | H3: 5 | I3: =H3-G3 -> 1 | J3: =IF(I3=0,"On Time",IF(I3<=2,"Minor Delay","Major Delay")) -> Minor Delay | K3: =H3-I3 -> 4 | L3: =IF(I3=0,0.3,I3) -> 1
A4: {=INDEX({"Jan","Feb","Mar"},ROUNDUP(ROW(A3)/15,0))} -> Jan | B4: {=INDEX(Task_Master!A$2:A$16,MOD(ROW()-2,15)+1)} -> 3 | C4: {=INDEX(Task_Master!B:B,MOD(ROW(A3)-1,15)+2)} -> AR | D4: {=INDEX(Task_Master!C:C,MOD(ROW(A3)-1,15)+2)} -> Customer Invoice Posting | E4: {=INDEX(Task_Master!D:D,MOD(ROW(A3)-1,15)+2)} -> Accounts Receivable | F4: {=INDEX(Task_Master!E:E,MOD(ROW(A3)-1,15)+2)} -> None | G4: 3 | H4: 3 | I4: =H4-G4 -> 0 | J4: =IF(I4=0,"On Time",IF(I4<=2,"Minor Delay","Major Delay")) -> On Time | K4: =H4-I4 -> 3 | L4: =IF(I4=0,0.3,I4) -> 0.3 | O4: Month | P4: Planned Close Day | Q4: Actual Close day
A5: {=INDEX({"Jan","Feb","Mar"},ROUNDUP(ROW(A4)/15,0))} -> Jan | B5: {=INDEX(Task_Master!A$2:A$16,MOD(ROW()-2,15)+1)} -> 4 | C5: {=INDEX(Task_Master!B:B,MOD(ROW(A4)-1,15)+2)} -> AR | D5: {=INDEX(Task_Master!C:C,MOD(ROW(A4)-1,15)+2)} -> AR Reconciliation | E5: {=INDEX(Task_Master!D:D,MOD(ROW(A4)-1,15)+2)} -> Accounts Receivable | F5: {=INDEX(Task_Master!E:E,MOD(ROW(A4)-1,15)+2)} -> 3 | G5: 5 | H5: 5 | I5: =H5-G5 -> 0 | J5: =IF(I5=0,"On Time",IF(I5<=2,"Minor Delay","Major Delay")) -> On Time | K5: =H5-I5 -> 5 | L5: =IF(I5=0,0.3,I5) -> 0.3 | O5: Jan | P5: 10 | Q5: 10
A6: {=INDEX({"Jan","Feb","Mar"},ROUNDUP(ROW(A5)/15,0))} -> Jan | B6: {=INDEX(Task_Master!A$2:A$16,MOD(ROW()-2,15)+1)} -> 5 | C6: {=INDEX(Task_Master!B:B,MOD(ROW(A5)-1,15)+2)} -> Payroll | D6: {=INDEX(Task_Master!C:C,MOD(ROW(A5)-1,15)+2)} -> Salary Processing | E6: {=INDEX(Task_Master!D:D,MOD(ROW(A5)-1,15)+2)} -> HR/Payroll | F6: {=INDEX(Task_Master!E:E,MOD(ROW(A5)-1,15)+2)} -> None | G6: 4 | H6: 6 | I6: =H6-G6 -> 2 | J6: =IF(I6=0,"On Time",IF(I6<=2,"Minor Delay","Major Delay")) -> Minor Delay | K6: =H6-I6 -> 4 | L6: =IF(I6=0,0.3,I6) -> 2 | O6: Feb | P6: 15 | Q6: 16
A7: {=INDEX({"Jan","Feb","Mar"},ROUNDUP(ROW(A6)/15,0))} -> Jan | B7: {=INDEX(Task_Master!A$2:A$16,MOD(ROW()-2,15)+1)} -> 6 | C7: {=INDEX(Task_Master!B:B,MOD(ROW(A6)-1,15)+2)} -> Payroll | D7: {=INDEX(Task_Master!C:C,MOD(ROW(A6)-1,15)+2)} -> Payroll Journal Entry | E7: {=INDEX(Task_Master!D:D,MOD(ROW(A6)-1,15)+2)} -> Finance | F7: {=INDEX(Task_Master!E:E,MOD(ROW(A6)-1,15)+2)} -> 5 | G7: 6 | H7: 7 | I7: =H7-G7 -> 1 | J7: =IF(I7=0,"On Time",IF(I7<=2,"Minor Delay","Major Delay")) -> Minor Delay | K7: =H7-I7 -> 6 | L7: =IF(I7=0,0.3,I7) -> 1 | O7: Mar | P7: 12 | Q7: 15
A8: {=INDEX({"Jan","Feb","Mar"},ROUNDUP(ROW(A7)/15,0))} -> Jan | B8: {=INDEX(Task_Master!A$2:A$16,MOD(ROW()-2,15)+1)} -> 7 | C8: {=INDEX(Task_Master!B:B,MOD(ROW(A7)-1,15)+2)} -> Inventory | D8: {=INDEX(Task_Master!C:C,MOD(ROW(A7)-1,15)+2)} -> Inventory Count | E8: {=INDEX(Task_Master!D:D,MOD(ROW(A7)-1,15)+2)} -> Operations | F8: {=INDEX(Task_Master!E:E,MOD(ROW(A7)-1,15)+2)} -> None | G8: 2 | H8: 5 | I8: =H8-G8 -> 3 | J8: =IF(I8=0,"On Time",IF(I8<=2,"Minor Delay","Major Delay")) -> Major Delay | K8: =H8-I8 -> 2 | L8: =IF(I8=0,0.3,I8) -> 3
A9: {=INDEX({"Jan","Feb","Mar"},ROUNDUP(ROW(A8)/15,0))} -> Jan | B9: {=INDEX(Task_Master!A$2:A$16,MOD(ROW()-2,15)+1)} -> 8 | C9: {=INDEX(Task_Master!B:B,MOD(ROW(A8)-1,15)+2)} -> Inventory | D9: {=INDEX(Task_Master!C:C,MOD(ROW(A8)-1,15)+2)} -> Inventory Valuation | E9: {=INDEX(Task_Master!D:D,MOD(ROW(A8)-1,15)+2)} -> Finance | F9: {=INDEX(Task_Master!E:E,MOD(ROW(A8)-1,15)+2)} -> 7 | G9: 3 | H9: 5 | I9: =H9-G9 -> 2 | J9: =IF(I9=0,"On Time",IF(I9<=2,"Minor Delay","Major Delay")) -> Minor Delay | K9: =H9-I9 -> 3 | L9: =IF(I9=0,0.3,I9) -> 2
A10: {=INDEX({"Jan","Feb","Mar"},ROUNDUP(ROW(A9)/15,0))} -> Jan | B10: {=INDEX(Task_Master!A$2:A$16,MOD(ROW()-2,15)+1)} -> 9 | C10: {=INDEX(Task_Master!B:B,MOD(ROW(A9)-1,15)+2)} -> Cash | D10: {=INDEX(Task_Master!C:C,MOD(ROW(A9)-1,15)+2)} -> Bank Reconciliation | E10: {=INDEX(Task_Master!D:D,MOD(ROW(A9)-1,15)+2)} -> Treasury | F10: {=INDEX(Task_Master!E:E,MOD(ROW(A9)-1,15)+2)} -> 1,3 | G10: 5 | H10: 7 | I10: =H10-G10 -> 2 | J10: =IF(I10=0,"On Time",IF(I10<=2,"Minor Delay","Major Delay")) -> Minor Delay | K10: =H10-I10 -> 5 | L10: =IF(I10=0,0.3,I10) -> 2
A11: {=INDEX({"Jan","Feb","Mar"},ROUNDUP(ROW(A10)/15,0))} -> Jan | B11: {=INDEX(Task_Master!A$2:A$16,MOD(ROW()-2,15)+1)} -> 10 | C11: {=INDEX(Task_Master!B:B,MOD(ROW(A10)-1,15)+2)} -> Fixed Assets | D11: {=INDEX(Task_Master!C:C,MOD(ROW(A10)-1,15)+2)} -> Depreciation Run | E11: {=INDEX(Task_Master!D:D,MOD(ROW(A10)-1,15)+2)} -> Finance | F11: {=INDEX(Task_Master!E:E,MOD(ROW(A10)-1,15)+2)} -> None | G11: 1 | H11: 1 | I11: =H11-G11 -> 0 | J11: =IF(I11=0,"On Time",IF(I11<=2,"Minor Delay","Major Delay")) -> On Time | K11: =H11-I11 -> 1 | L11: =IF(I11=0,0.3,I11) -> 0.3
A12: {=INDEX({"Jan","Feb","Mar"},ROUNDUP(ROW(A11)/15,0))} -> Jan | B12: {=INDEX(Task_Master!A$2:A$16,MOD(ROW()-2,15)+1)} -> 11 | C12: {=INDEX(Task_Master!B:B,MOD(ROW(A11)-1,15)+2)} -> Accruals | D12: {=INDEX(Task_Master!C:C,MOD(ROW(A11)-1,15)+2)} -> Expense Accrual Posting | E12: {=INDEX(Task_Master!D:D,MOD(ROW(A11)-1,15)+2)} -> Finance | F12: {=INDEX(Task_Master!E:E,MOD(ROW(A11)-1,15)+2)} -> 2,4,8 | G12: 6 | H12: 7 | I12: =H12-G12 -> 1 | J12: =IF(I12=0,"On Time",IF(I12<=2,"Minor Delay","Major Delay")) -> Minor Delay | K12: =H12-I12 -> 6 | L12: =IF(I12=0,0.3,I12) -> 1
A13: {=INDEX({"Jan","Feb","Mar"},ROUNDUP(ROW(A12)/15,0))} -> Jan | B13: {=INDEX(Task_Master!A$2:A$16,MOD(ROW()-2,15)+1)} -> 12 | C13: {=INDEX(Task_Master!B:B,MOD(ROW(A12)-1,15)+2)} -> Reporting | D13: {=INDEX(Task_Master!C:C,MOD(ROW(A12)-1,15)+2)} -> Trial Balance Review | E13: {=INDEX(Task_Master!D:D,MOD(ROW(A12)-1,15)+2)} -> Finance | F13: {=INDEX(Task_Master!E:E,MOD(ROW(A12)-1,15)+2)} -> 6,9,10,11 | G13: 7 | H13: 8 | I13: =H13-G13 -> 1 | J13: =IF(I13=0,"On Time",IF(I13<=2,"Minor Delay","Major Delay")) -> Minor Delay | K13: =H13-I13 -> 7 | L13: =IF(I13=0,0.3,I13) -> 1 | O13: Month | P13: Actual Close Day
A14: {=INDEX({"Jan","Feb","Mar"},ROUNDUP(ROW(A13)/15,0))} -> Jan | B14: {=INDEX(Task_Master!A$2:A$16,MOD(ROW()-2,15)+1)} -> 13 | C14: {=INDEX(Task_Master!B:B,MOD(ROW(A13)-1,15)+2)} -> Reporting | D14: {=INDEX(Task_Master!C:C,MOD(ROW(A13)-1,15)+2)} -> Financial Statement Prep | E14: {=INDEX(Task_Master!D:D,MOD(ROW(A13)-1,15)+2)} -> Finance | F14: {=INDEX(Task_Master!E:E,MOD(ROW(A13)-1,15)+2)} -> 12 | G14: 8 | H14: 9 | I14: =H14-G14 -> 1 | J14: =IF(I14=0,"On Time",IF(I14<=2,"Minor Delay","Major Delay")) -> Minor Delay | K14: =H14-I14 -> 8 | L14: =IF(I14=0,0.3,I14) -> 1 | O14: Jan | P14: 10
A15: {=INDEX({"Jan","Feb","Mar"},ROUNDUP(ROW(A14)/15,0))} -> Jan | B15: {=INDEX(Task_Master!A$2:A$16,MOD(ROW()-2,15)+1)} -> 14 | C15: {=INDEX(Task_Master!B:B,MOD(ROW(A14)-1,15)+2)} -> Reporting | D15: {=INDEX(Task_Master!C:C,MOD(ROW(A14)-1,15)+2)} -> Management Review | E15: {=INDEX(Task_Master!D:D,MOD(ROW(A14)-1,15)+2)} -> CFO Office | F15: {=INDEX(Task_Master!E:E,MOD(ROW(A14)-1,15)+2)} -> 13 | G15: 9 | H15: 9 | I15: =H15-G15 -> 0 | J15: =IF(I15=0,"On Time",IF(I15<=2,"Minor Delay","Major Delay")) -> On Time | K15: =H15-I15 -> 9 | L15: =IF(I15=0,0.3,I15) -> 0.3 | O15: Feb | P15: 16
A16: {=INDEX({"Jan","Feb","Mar"},ROUNDUP(ROW(A15)/15,0))} -> Jan | B16: {=INDEX(Task_Master!A$2:A$16,MOD(ROW()-2,15)+1)} -> 15 | C16: {=INDEX(Task_Master!B:B,MOD(ROW(A15)-1,15)+2)} -> Reporting | D16: {=INDEX(Task_Master!C:C,MOD(ROW(A15)-1,15)+2)} -> Books Closed | E16: {=INDEX(Task_Master!D:D,MOD(ROW(A15)-1,15)+2)} -> Finance | F16: {=INDEX(Task_Master!E:E,MOD(ROW(A15)-1,15)+2)} -> 14 | G16: 10 | H16: 10 | I16: =H16-G16 -> 0 | J16: =IF(I16=0,"On Time",IF(I16<=2,"Minor Delay","Major Delay")) -> On Time | K16: =H16-I16 -> 10 | L16: =IF(I16=0,0.3,I16) -> 0.3 | O16: Mar | P16: 15
A17: {=INDEX({"Jan","Feb","Mar"},ROUNDUP(ROW(A16)/15,0))} -> Feb | B17: {=INDEX(Task_Master!A$2:A$16,MOD(ROW()-2,15)+1)} -> 1 | C17: {=INDEX(Task_Master!B:B,MOD(ROW(A16)-1,15)+2)} -> AP | D17: {=INDEX(Task_Master!C:C,MOD(ROW(A16)-1,15)+2)} -> Vendor Invoice Posting | E17: {=INDEX(Task_Master!D:D,MOD(ROW(A16)-1,15)+2)} -> Accounts Payable | F17: {=INDEX(Task_Master!E:E,MOD(ROW(A16)-1,15)+2)} -> None | G17: 4 | H17: 4 | I17: =H17-G17 -> 0 | J17: =IF(I17=0,"On Time",IF(I17<=2,"Minor Delay","Major Delay")) -> On Time | K17: =H17-I17 -> 4 | L17: =IF(I17=0,0.3,I17) -> 0.3
A18: {=INDEX({"Jan","Feb","Mar"},ROUNDUP(ROW(A17)/15,0))} -> Feb | B18: {=INDEX(Task_Master!A$2:A$16,MOD(ROW()-2,15)+1)} -> 2 | C18: {=INDEX(Task_Master!B:B,MOD(ROW(A17)-1,15)+2)} -> AP | D18: {=INDEX(Task_Master!C:C,MOD(ROW(A17)-1,15)+2)} -> AP Reconciliation | E18: {=INDEX(Task_Master!D:D,MOD(ROW(A17)-1,15)+2)} -> Accounts Payable | F18: {=INDEX(Task_Master!E:E,MOD(ROW(A17)-1,15)+2)} -> 1 | G18: 5 | H18: 6 | I18: =H18-G18 -> 1 | J18: =IF(I18=0,"On Time",IF(I18<=2,"Minor Delay","Major Delay")) -> Minor Delay | K18: =H18-I18 -> 5 | L18: =IF(I18=0,0.3,I18) -> 1
A19: {=INDEX({"Jan","Feb","Mar"},ROUNDUP(ROW(A18)/15,0))} -> Feb | B19: {=INDEX(Task_Master!A$2:A$16,MOD(ROW()-2,15)+1)} -> 3 | C19: {=INDEX(Task_Master!B:B,MOD(ROW(A18)-1,15)+2)} -> AR | D19: {=INDEX(Task_Master!C:C,MOD(ROW(A18)-1,15)+2)} -> Customer Invoice Posting | E19: {=INDEX(Task_Master!D:D,MOD(ROW(A18)-1,15)+2)} -> Accounts Receivable | F19: {=INDEX(Task_Master!E:E,MOD(ROW(A18)-1,15)+2)} -> None | G19: 4 | H19: 5 | I19: =H19-G19 -> 1 | J19: =IF(I19=0,"On Time",IF(I19<=2,"Minor Delay","Major Delay")) -> Minor Delay | K19: =H19-I19 -> 4 | L19: =IF(I19=0,0.3,I19) -> 1
A20: {=INDEX({"Jan","Feb","Mar"},ROUNDUP(ROW(A19)/15,0))} -> Feb | B20: {=INDEX(Task_Master!A$2:A$16,MOD(ROW()-2,15)+1)} -> 4 | C20: {=INDEX(Task_Master!B:B,MOD(ROW(A19)-1,15)+2)} -> AR | D20: {=INDEX(Task_Master!C:C,MOD(ROW(A19)-1,15)+2)} -> AR Reconciliation | E20: {=INDEX(Task_Master!D:D,MOD(ROW(A19)-1,15)+2)} -> Accounts Receivable | F20: {=INDEX(Task_Master!E:E,MOD(ROW(A19)-1,15)+2)} -> 3 | G20: 5 | H20: 5 | I20: =H20-G20 -> 0 | J20: =IF(I20=0,"On Time",IF(I20<=2,"Minor Delay","Major Delay")) -> On Time | K20: =H20-I20 -> 5 | L20: =IF(I20=0,0.3,I20) -> 0.3
A21: {=INDEX({"Jan","Feb","Mar"},ROUNDUP(ROW(A20)/15,0))} -> Feb | B21: {=INDEX(Task_Master!A$2:A$16,MOD(ROW()-2,15)+1)} -> 5 | C21: {=INDEX(Task_Master!B:B,MOD(ROW(A20)-1,15)+2)} -> Payroll | D21: {=INDEX(Task_Master!C:C,MOD(ROW(A20)-1,15)+2)} -> Salary Processing | E21: {=INDEX(Task_Master!D:D,MOD(ROW(A20)-1,15)+2)} -> HR/Payroll | F21: {=INDEX(Task_Master!E:E,MOD(ROW(A20)-1,15)+2)} -> None | G21: 6 | H21: 8 | I21: =H21-G21 -> 2 | J21: =IF(I21=0,"On Time",IF(I21<=2,"Minor Delay","Major Delay")) -> Minor Delay | K21: =H21-I21 -> 6 | L21: =IF(I21=0,0.3,I21) -> 2
A22: {=INDEX({"Jan","Feb","Mar"},ROUNDUP(ROW(A21)/15,0))} -> Feb | B22: {=INDEX(Task_Master!A$2:A$16,MOD(ROW()-2,15)+1)} -> 6 | C22: {=INDEX(Task_Master!B:B,MOD(ROW(A21)-1,15)+2)} -> Payroll | D22: {=INDEX(Task_Master!C:C,MOD(ROW(A21)-1,15)+2)} -> Payroll Journal Entry | E22: {=INDEX(Task_Master!D:D,MOD(ROW(A21)-1,15)+2)} -> Finance | F22: {=INDEX(Task_Master!E:E,MOD(ROW(A21)-1,15)+2)} -> 5 | G22: 7 | H22: 9 | I22: =H22-G22 -> 2 | J22: =IF(I22=0,"On Time",IF(I22<=2,"Minor Delay","Major Delay")) -> Minor Delay | K22: =H22-I22 -> 7 | L22: =IF(I22=0,0.3,I22) -> 2
A23: {=INDEX({"Jan","Feb","Mar"},ROUNDUP(ROW(A22)/15,0))} -> Feb | B23: {=INDEX(Task_Master!A$2:A$16,MOD(ROW()-2,15)+1)} -> 7 | C23: {=INDEX(Task_Master!B:B,MOD(ROW(A22)-1,15)+2)} -> Inventory | D23: {=INDEX(Task_Master!C:C,MOD(ROW(A22)-1,15)+2)} -> Inventory Count | E23: {=INDEX(Task_Master!D:D,MOD(ROW(A22)-1,15)+2)} -> Operations | F23: {=INDEX(Task_Master!E:E,MOD(ROW(A22)-1,15)+2)} -> None | G23: 8 | H23: 9 | I23: =H23-G23 -> 1 | J23: =IF(I23=0,"On Time",IF(I23<=2,"Minor Delay","Major Delay")) -> Minor Delay | K23: =H23-I23 -> 8 | L23: =IF(I23=0,0.3,I23) -> 1
A24: {=INDEX({"Jan","Feb","Mar"},ROUNDUP(ROW(A23)/15,0))} -> Feb | B24: {=INDEX(Task_Master!A$2:A$16,MOD(ROW()-2,15)+1)} -> 8 | C24: {=INDEX(Task_Master!B:B,MOD(ROW(A23)-1,15)+2)} -> Inventory | D24: {=INDEX(Task_Master!C:C,MOD(ROW(A23)-1,15)+2)} -> Inventory Valuation | E24: {=INDEX(Task_Master!D:D,MOD(ROW(A23)-1,15)+2)} -> Finance | F24: {=INDEX(Task_Master!E:E,MOD(ROW(A23)-1,15)+2)} -> 7 | G24: 9 | H24: 10 | I24: =H24-G24 -> 1 | J24: =IF(I24=0,"On Time",IF(I24<=2,"Minor Delay","Major Delay")) -> Minor Delay | K24: =H24-I24 -> 9 | L24: =IF(I24=0,0.3,I24) -> 1
A25: {=INDEX({"Jan","Feb","Mar"},ROUNDUP(ROW(A24)/15,0))} -> Feb | B25: {=INDEX(Task_Master!A$2:A$16,MOD(ROW()-2,15)+1)} -> 9 | C25: {=INDEX(Task_Master!B:B,MOD(ROW(A24)-1,15)+2)} -> Cash | D25: {=INDEX(Task_Master!C:C,MOD(ROW(A24)-1,15)+2)} -> Bank Reconciliation | E25: {=INDEX(Task_Master!D:D,MOD(ROW(A24)-1,15)+2)} -> Treasury | F25: {=INDEX(Task_Master!E:E,MOD(ROW(A24)-1,15)+2)} -> 1,3 | G25: 6 | H25: 6 | I25: =H25-G25 -> 0 | J25: =IF(I25=0,"On Time",IF(I25<=2,"Minor Delay","Major Delay")) -> On Time | K25: =H25-I25 -> 6 | L25: =IF(I25=0,0.3,I25) -> 0.3
A26: {=INDEX({"Jan","Feb","Mar"},ROUNDUP(ROW(A25)/15,0))} -> Feb | B26: {=INDEX(Task_Master!A$2:A$16,MOD(ROW()-2,15)+1)} -> 10 | C26: {=INDEX(Task_Master!B:B,MOD(ROW(A25)-1,15)+2)} -> Fixed Assets | D26: {=INDEX(Task_Master!C:C,MOD(ROW(A25)-1,15)+2)} -> Depreciation Run | E26: {=INDEX(Task_Master!D:D,MOD(ROW(A25)-1,15)+2)} -> Finance | F26: {=INDEX(Task_Master!E:E,MOD(ROW(A25)-1,15)+2)} -> None | G26: 7 | H26: 10 | I26: =H26-G26 -> 3 | J26: =IF(I26=0,"On Time",IF(I26<=2,"Minor Delay","Major Delay")) -> Major Delay | K26: =H26-I26 -> 7 | L26: =IF(I26=0,0.3,I26) -> 3
A27: {=INDEX({"Jan","Feb","Mar"},ROUNDUP(ROW(A26)/15,0))} -> Feb | B27: {=INDEX(Task_Master!A$2:A$16,MOD(ROW()-2,15)+1)} -> 11 | C27: {=INDEX(Task_Master!B:B,MOD(ROW(A26)-1,15)+2)} -> Accruals | D27: {=INDEX(Task_Master!C:C,MOD(ROW(A26)-1,15)+2)} -> Expense Accrual Posting | E27: {=INDEX(Task_Master!D:D,MOD(ROW(A26)-1,15)+2)} -> Finance | F27: {=INDEX(Task_Master!E:E,MOD(ROW(A26)-1,15)+2)} -> 2,4,8 | G27: 10 | H27: 13 | I27: =H27-G27 -> 3 | J27: =IF(I27=0,"On Time",IF(I27<=2,"Minor Delay","Major Delay")) -> Major Delay | K27: =H27-I27 -> 10 | L27: =IF(I27=0,0.3,I27) -> 3
A28: {=INDEX({"Jan","Feb","Mar"},ROUNDUP(ROW(A27)/15,0))} -> Feb | B28: {=INDEX(Task_Master!A$2:A$16,MOD(ROW()-2,15)+1)} -> 12 | C28: {=INDEX(Task_Master!B:B,MOD(ROW(A27)-1,15)+2)} -> Reporting | D28: {=INDEX(Task_Master!C:C,MOD(ROW(A27)-1,15)+2)} -> Trial Balance Review | E28: {=INDEX(Task_Master!D:D,MOD(ROW(A27)-1,15)+2)} -> Finance | F28: {=INDEX(Task_Master!E:E,MOD(ROW(A27)-1,15)+2)} -> 6,9,10,11 | G28: 12 | H28: 13 | I28: =H28-G28 -> 1 | J28: =IF(I28=0,"On Time",IF(I28<=2,"Minor Delay","Major Delay")) -> Minor Delay | K28: =H28-I28 -> 12 | L28: =IF(I28=0,0.3,I28) -> 1
... A46: {=INDEX({"Jan","Feb","Mar"},ROUNDUP(ROW(A45)/15,0))} -> Mar | B46: {=INDEX(Task_Master!A$2:A$16,MOD(ROW()-2,15)+1)} -> 15 | C46: {=INDEX(Task_Master!B:B,MOD(ROW(A45)-1,15)+2)} -> Reporting | D46: {=INDEX(Task_Master!C:C,MOD(ROW(A45)-1,15)+2)} -> Books Closed | E46: {=INDEX(Task_Master!D:D,MOD(ROW(A45)-1,15)+2)} -> Finance | F46: {=INDEX(Task_Master!E:E,MOD(ROW(A45)-1,15)+2)} -> 14 | G46: 12 | H46: 15 | I46: =H46-G46 -> 3 | J46: =IF(I46=0,"On Time",IF(I46<=2,"Minor Delay","Major Delay")) -> Major Delay | K46: =H46-I46 -> 12 | L46: =IF(I46=0,0.3,I46) -> 3

Sheet timeline
B1: Task_Name | C1: Start_Day | D1: Duration
B2: Vendor Invoice Posting | C2: 2 | D2: 0.3
B3: AP Reconciliation | C3: 4 | D3: 1
B4: Customer Invoice Posting | C4: 3 | D4: 0.3
B5: AR Reconciliation | C5: 5 | D5: 0.3
B6: Salary Processing | C6: 4 | D6: 2
B7: Payroll Journal Entry | C7: 6 | D7: 1
B8: Inventory Count | C8: 2 | D8: 3
B9: Inventory Valuation | C9: 3 | D9: 2
B10: Bank Reconciliation | C10: 5 | D10: 2
B11: Depreciation Run | C11: 1 | D11: 0.3
B12: Expense Accrual Posting | C12: 6 | D12: 1
B13: Trial Balance Review | C13: 7 | D13: 1
... B16: Books Closed | C16: 10 | D16: 0.3
